README.md
rsyncy
rsyncy-stat
rsyncy.py
setup.py
rsyncy.egg-info/PKG-INFO
rsyncy.egg-info/SOURCES.txt
rsyncy.egg-info/dependency_links.txt
rsyncy.egg-info/top_level.txt