Metadata-Version: 2.4
Name: rsyncy
Version: 2.1.0
Summary: A status/progress bar for rsync.
Home-page: https://github.com/laktak/rsyncy
Author: Christian Zangl
Author-email: laktak@cdak.net
Dynamic: author
Dynamic: author-email
Dynamic: description
Dynamic: description-content-type
Dynamic: home-page
Dynamic: summary
